adder.v
// Adder circuit
`define AND and #50
`define OR or #50
`define NOT not #50
`define XOR xor #50
`define NAND nand #50
module behavioralFullAdder
(
    output sum, 
    output carryout,
    input a, 
    input b, 
    input carryin
);
    // Uses concatenation operator and built-in '+'
    assign {carryout, sum}=a+b+carryin;
endmodule

module structuralFullAdder
(
    output sum, 
    output carryout,
    input a, 
    input b, 
    input carryin
    
);
    wire n1,n2,n3,x1;
    `AND AandB(n1,a,b);
    `AND AandC(n2,a,carryin);
    `AND CandB(n3,carryin,b);
    `OR Cout(carryout,n1,n2,n3);
    `XOR AorB(x1,a,b);
    `XOR AorC(sum,x1,carryin);
endmodule

adder.t.v
// Adder testbench
`timescale 1 ns / 1 ps
`include "adder.v"

module testFullAdder();
    reg a, b, carryin;
    wire sum, carryout;

    structuralFullAdder adder (sum, carryout, a, b, carryin);

    initial begin
    $display("A B| Carryin | Sum Carryout");
    a=0;b=0;carryin=0; #1000 
    $display("%b  %b  %b | %b  %b | ", a, b, carryin, sum, carryout);
    a=0;b=1;carryin=0; #1000 
    $display("%b  %b  %b | %b  %b | ", a, b, carryin, sum, carryout);
    a=1;b=0;carryin=0; #1000 
    $display("%b  %b  %b | %b  %b | ", a, b, carryin, sum, carryout);
    a=1;b=1;carryin=0; #1000 
    $display("%b  %b  %b | %b  %b | ", a, b, carryin, sum, carryout);
    a=0;b=0;carryin=1; #1000 
    $display("%b  %b  %b | %b  %b | ", a, b, carryin, sum, carryout);
    a=0;b=1;carryin=1; #1000 
    $display("%b  %b  %b | %b  %b | ", a, b, carryin, sum, carryout);
    a=1;b=0;carryin=1; #1000 
    $display("%b  %b  %b | %b  %b | ", a, b, carryin, sum, carryout);
    a=1;b=1;carryin=1; #1000 
    $display("%b  %b  %b | %b  %b | ", a, b, carryin, sum, carryout);
    end
    initial begin
    a=0;b=0;carryin=0; #1000
    $dumpfile("adder.vcd"); 
    $dumpvars(0, testFullAdder);
    
    end
endmodule

adder.vcd
$date
	Thu Sep 20 20:22:30 2018
$end
$version
	Icarus Verilog
$end
$timescale
	1ps
$end
$scope module testFullAdder $end
$var wire 1 ! sum $end
$var wire 1 " carryout $end
$var reg 1 # a $end
$var reg 1 $ b $end
$var reg 1 % carryin $end
$scope module adder $end
$var wire 1 # a $end
$var wire 1 $ b $end
$var wire 1 % carryin $end
$var wire 1 " carryout $end
$var wire 1 & n1 $end
$var wire 1 ' n2 $end
$var wire 1 ( n3 $end
$var wire 1 ! sum $end
$var wire 1 ) x1 $end
$upscope $end
$upscope $end
$enddefinitions $end
#1000000
$dumpvars
0)
0(
0'
0&
0%
1$
0#
0"
0!
$end
#1050000
1)
#1100000
1!
#2000000
0$
1#
#3000000
1$
#3050000
1&
0)
#3100000
1"
0!
#4000000
1%
0$
0#
#4050000
1!
0&
#4100000
0"
#5000000
1$
#5050000
1(
1)
#5100000
1"
0!
#6000000
0$
1#
#6050000
0(
1'
#7000000
1$
#7050000
1&
1(
0)
#7100000
1!
